[
  {
    "collection": "rams",
    "name": "OLOy DDR4 RAM 32GB (2x16GB) Warhawk Aura Sync RGB 3600 MHz CL18 1.35V 288-Pin Desktop Gaming UDIMM (MD4U163618DEDA)",
    "issue": "No link field found (checked: sourceUrl, url, link, amazonLink)",
    "id": "69082e5ae05902f2be411114"
  },
  {
    "collection": "cases",
    "name": "NZXT H510",
    "issue": "No link field found (checked: sourceUrl, url, link, amazonLink)",
    "id": "68aa6dec78f87428fb81de2a"
  },
  {
    "collection": "cases",
    "name": "K6 PC Case - Pre-Installed 6 PWM ARGB Fan (3 x 120mm, 3 x 140mm), ATX Mid-Tower Gaming PC Case, with Type-C, FOIFKIN (Black, K6)",
    "issue": "No link field found (checked: sourceUrl, url, link, amazonLink)",
    "id": "6921689b26218241f91ec294"
  },
  {
    "collection": "storages",
    "name": "2TB NVMe SSD Gen4x4 for PS5 with Heatsink, M.2 2280 PCIe 4.0 Gaming SSD, PS5 Storage Expansion, Up to 7500MB/s Read & 6800MB/s Write, DRAM Cache, 3D TLC NAND",
    "issue": "No link field found (checked: sourceUrl, url, link, amazonLink)",
    "id": "691164c9c9778f85fbcb97f6"
  }
]